redismutex/__init__.py
redismutex/decorators.py
redismutex/errors.py
redismutex/mutex.py
redismutex-1.0.0.dist-info/METADATA
redismutex-1.0.0.dist-info/RECORD
redismutex-1.0.0.dist-info/WHEEL
redismutex-1.0.0.dist-info/top_level.txt
